libhikvision/__init__.py
libhikvision-0.3.10.dist-info/licenses/LICENSE
libhikvision-0.3.10.dist-info/METADATA
libhikvision-0.3.10.dist-info/WHEEL
libhikvision-0.3.10.dist-info/top_level.txt
libhikvision-0.3.10.dist-info/RECORD
