Metadata-Version: 2.4
Name: libhikvision
Version: 0.3.10
Summary: Parse Hikvision datadirs that Hikvision IP cameras store the videos
Home-page: https://github.com/bkbilly/libHikvision
Author: bkbilly
Author-email: bkbilly@hotmail.com
Classifier: Programming Language :: Python :: 3
Classifier: License :: OSI Approved :: MIT License
Classifier: Operating System :: OS Independent
License-File: LICENSE
Requires-Dist: pytz>=2019.2
Dynamic: author
Dynamic: author-email
Dynamic: classifier
Dynamic: description
Dynamic: description-content-type
Dynamic: home-page
Dynamic: license-file
Dynamic: requires-dist
Dynamic: summary
